dora_sam2/__init__.py
dora_sam2/__main__.py
dora_sam2/main.py
dora_sam2-0.4.1.dist-info/METADATA
dora_sam2-0.4.1.dist-info/WHEEL
dora_sam2-0.4.1.dist-info/entry_points.txt
dora_sam2-0.4.1.dist-info/top_level.txt
dora_sam2-0.4.1.dist-info/RECORD
