Metadata-Version: 2.4
Name: dora-sam2
Version: 0.4.1
Summary: dora-sam2
Author-email: Your Name <email@email.com>
License: MIT
Requires-Python: >=3.10
Requires-Dist: dora-rs>=0.3.9
Requires-Dist: huggingface-hub>=0.29.0
Requires-Dist: opencv-python>=4.11.0.86
Requires-Dist: sam2>=1.1.0
